README.rst
setup.py
OTRXMPPLogger.egg-info/PKG-INFO
OTRXMPPLogger.egg-info/SOURCES.txt
OTRXMPPLogger.egg-info/dependency_links.txt
OTRXMPPLogger.egg-info/requires.txt
OTRXMPPLogger.egg-info/top_level.txt
otrxmpplogger/__init__.py