Metadata-Version: 1.1
Name: OTRXMPPLogger
Version: 1.0.1
Summary: Logging with OTR (Off-the-Record Messaging) and XMPP
Home-page: https://github.com/mikegogulski/python-otrxmpplogger
Author: Mike Gogulski
Author-email: mike@gogulski.com
License: Unlicense
Platform: UNKNOWN
Classifier: Development Status :: 4 - Beta
Classifier: Intended Audience :: Developers
Classifier: License :: Public Domain
Classifier: Operating System :: OS Independent
Classifier: Programming Language :: Python
Classifier: Topic :: Communications :: Chat
Classifier: Topic :: Software Development :: Libraries :: Python Modules
Classifier: Topic :: System :: Logging
